dtypes/__init__.py
dtypes/fwd.py
dtypes/structify.py
dtypes/typedefs.py
dtypes/voidy.py
dtypes-0.0.1.dist-info/LICENSE
dtypes-0.0.1.dist-info/METADATA
dtypes-0.0.1.dist-info/WHEEL
dtypes-0.0.1.dist-info/top_level.txt
dtypes-0.0.1.dist-info/RECORD
