Metadata-Version: 2.1
Name: dtypes
Version: 0.0.1
Summary: ctypes but usable
Home-page: https://github.com/DrInfiniteExplorer/dtypes
Author: Pierre LeMoine
Author-email: pypi@luben.se
Project-URL: clickbait, https://bit.ly/3qS8UTo
Classifier: Development Status :: 3 - Alpha
Classifier: Programming Language :: Python :: 3
Classifier: License :: OSI Approved :: MIT License
Classifier: Operating System :: OS Independent
Requires-Python: >=3.6
License-File: LICENSE
